adagenes/__init__.py
adagenes/__main__.py
adagenes/cli.py
adagenes/app/__init__.py
adagenes/app/app_analyze.py
adagenes/app/app_annotate.py
adagenes/app/app_io.py
adagenes/app/app_load_data.py
adagenes/app/app_parse_data.py
adagenes/app/app_processing.py
adagenes/app/app_tools.py
adagenes/app/bframe_to_dataframe.py
adagenes/app/db_client.py
adagenes/app/filter.py
adagenes/app/run_liftover.py
adagenes/app/sample_data.py
adagenes/app/stats.py
adagenes/app/table.py
adagenes/app/transform_model.py
adagenes/app/sites/__init__.py
adagenes/app/sites/about.py
adagenes/clients/__init__.py
adagenes/clients/client.py
adagenes/clients/annotate/__init__.py
adagenes/clients/annotate/blosum_client.py
adagenes/clients/annotate/hgvs_notation.py
adagenes/clients/annotate/liftover_annotation.py
adagenes/clients/annotate/type_recognition.py
adagenes/clients/api_clients/__init__.py
adagenes/clients/api_clients/uniprot_client.py
adagenes/clients/filter/__init__.py
adagenes/clients/filter/allele_filter.py
adagenes/clients/filter/chrom_filter.py
adagenes/clients/filter/combined_filter.py
adagenes/clients/filter/defined_variant_filter.py
adagenes/clients/filter/filter_feature.py
adagenes/clients/filter/number_filter.py
adagenes/clients/filter/position_filter.py
adagenes/clients/filter/random_variant_filter.py
adagenes/clients/filter/section_filter.py
adagenes/clients/filter/text_filter.py
adagenes/clients/filter/type_filter.py
adagenes/clients/network/__init__.py
adagenes/clients/network/rest_client.py
adagenes/clients/plot/__init__.py
adagenes/clients/processor/__init__.py
adagenes/clients/processor/vcf_processor.py
adagenes/clients/reader/__init__.py
adagenes/clients/reader/avf_reader.py
adagenes/clients/reader/bed_reader.py
adagenes/clients/reader/csv_reader.py
adagenes/clients/reader/fasta_reader.py
adagenes/clients/reader/gtf_reader.py
adagenes/clients/reader/json_reader.py
adagenes/clients/reader/maf_reader.py
adagenes/clients/reader/reader.py
adagenes/clients/reader/tsv_reader.py
adagenes-0.5.3.dist-info/METADATA
adagenes-0.5.3.dist-info/WHEEL
adagenes-0.5.3.dist-info/entry_points.txt
adagenes-0.5.3.dist-info/top_level.txt
adagenes-0.5.3.dist-info/RECORD
