Metadata-Version: 2.1
Name: adagenes
Version: 0.5.3
Summary: Generic toolkit for processing DNA polymorphism data
Home-page: https://gitlab.gwdg.de/MedBioinf/mtb/adagenes
Author: Nadine S. Kurz
Author-email: nadine.kurz@bioinf.med.uni-goettingen.de
Classifier: Programming Language :: Python :: 3
Classifier: License :: OSI Approved :: GNU General Public License v3 (GPLv3)
Classifier: Operating System :: OS Independent
Requires-Python: >=3.9
Requires-Dist: requests
Requires-Dist: liftover
Requires-Dist: plotly
Requires-Dist: openpyxl
Requires-Dist: matplotlib
Requires-Dist: scikit-learn
Requires-Dist: blosum
Requires-Dist: pandas
Requires-Dist: python-magic
Requires-Dist: upsetplot
Requires-Dist: pyaml
Requires-Dist: numpy
Requires-Dist: flask
Requires-Dist: Flask-Cors
Requires-Dist: flask-swagger-ui
Requires-Dist: pymongo
Provides-Extra: extra
Requires-Dist: onkopus ; extra == 'extra'
